neurionpy/__init__.py
neurionpy/auth/__init__.py
neurionpy/auth/interface.py
neurionpy/auth/rest_client.py
neurionpy/bank/__init__.py
neurionpy/bank/interface.py
neurionpy/bank/rest_client.py
neurionpy/common/__init__.py
neurionpy/common/rest_client.py
neurionpy/common/types.py
neurionpy/common/utils.py
neurionpy/consensus/__init__.py
neurionpy/consensus/interface.py
neurionpy/consensus/rest_client.py
neurionpy/cosmwasm/__init__.py
neurionpy/cosmwasm/interface.py
neurionpy/cosmwasm/rest_client.py
neurionpy/crucible/__init__.py
neurionpy/crucible/interface.py
neurionpy/crucible/msg_client.py
neurionpy/crucible/rest_client.py
neurionpy/crypto/__init__.py
neurionpy/crypto/address.py
neurionpy/crypto/hashfuncs.py
neurionpy/crypto/interface.py
neurionpy/crypto/keypairs.py
neurionpy/distribution/__init__.py
neurionpy/distribution/interface.py
neurionpy/distribution/rest_client.py
neurionpy/evidence/__init__.py
neurionpy/evidence/interface.py
neurionpy/evidence/rest_client.py
neurionpy/fusion/__init__.py
neurionpy/fusion/interface.py
neurionpy/fusion/msg_client.py
neurionpy/fusion/rest_client.py
neurionpy/ganglion/__init__.py
neurionpy/ganglion/interface.py
neurionpy/ganglion/msg_client.py
neurionpy/ganglion/rest_client.py
neurionpy/gov/__init__.py
neurionpy/gov/interface.py
neurionpy/gov/rest_client.py
neurionpy/ibc/__init__.py
neurionpy/ibc/applications/transfer/__init__.py
neurionpy/ibc/applications/transfer/interface.py
neurionpy/ibc/applications/transfer/rest_client.py
neurionpy/ibc/core/channel/__init__.py
neurionpy/ibc/core/channel/interface.py
neurionpy/ibc/core/channel/rest_client.py
neurionpy/ibc/core/client/__init__.py
neurionpy/ibc/core/client/interface.py
neurionpy/ibc/core/client/rest_client.py
neurionpy/ibc/core/connection/__init__.py
neurionpy/ibc/core/connection/interface.py
neurionpy/ibc/core/connection/rest_client.py
neurionpy/mint/__init__.py
neurionpy/mint/interface.py
neurionpy/mint/rest_client.py
neurionpy/mnemonic/__init__.py
neurionpy-0.19.0.dist-info/METADATA
neurionpy-0.19.0.dist-info/WHEEL
neurionpy-0.19.0.dist-info/RECORD
