Metadata-Version: 2.3
Name: neurionpy
Version: 0.19.0
Summary: Python library with the neurion networks
License: Apache-2.0
Keywords: CosmPy,Cosmos-SDK
Author: Neurion.xyz Limited
Requires-Python: >=3.8,<4.0
Classifier: Environment :: Console
Classifier: Intended Audience :: Developers
Classifier: Intended Audience :: Information Technology
Classifier: License :: OSI Approved :: Apache Software License
Classifier: Natural Language :: English
Classifier: Operating System :: MacOS
Classifier: Operating System :: Microsoft :: Windows
Classifier: Operating System :: Unix
Classifier: Programming Language :: Python :: 3
Classifier: Programming Language :: Python :: 3.8
Classifier: Programming Language :: Python :: 3.9
Classifier: Programming Language :: Python :: 3.10
Classifier: Programming Language :: Python :: 3.11
Classifier: Programming Language :: Python :: 3.12
Classifier: Programming Language :: Python :: 3.13
Classifier: Topic :: Software Development
Classifier: Topic :: Software Development :: Libraries :: Python Modules
Classifier: Topic :: System
Requires-Dist: bech32
Requires-Dist: coincurve (>=20.0.0,<21.0.0)
Requires-Dist: ecdsa
Requires-Dist: googleapis-common-protos
Requires-Dist: grpcio (==1.70.0)
Requires-Dist: grpcio-tools (==1.70.0)
Requires-Dist: jsonschema (>=3.2.0,<5)
Requires-Dist: protobuf (==5.29.3)
Requires-Dist: pycryptodome (>=3.18.0,<4.0.0)
Requires-Dist: pytest (>=8.3.4,<9.0.0)
Requires-Dist: python-dateutil
Requires-Dist: requests
Project-URL: Documentation, https://github.com/neurion-xyz/neurionpy
Project-URL: Homepage, https://github.com/neurion-xyz/neurionpy
Project-URL: Repository, https://github.com/neurion-xyz/neurionpy
